[ {
  "localidade" : "2508208",
  "sexo" : null,
  "res" : [ {
    "nome" : "MARIA",
    "frequencia" : 1060,
    "ranking" : 1
  }, {
    "nome" : "JOSE",
    "frequencia" : 583,
    "ranking" : 2
  }, {
    "nome" : "JOAO",
    "frequencia" : 175,
    "ranking" : 3
  }, {
    "nome" : "SEVERINO",
    "frequencia" : 171,
    "ranking" : 4
  }, {
    "nome" : "ANTONIO",
    "frequencia" : 170,
    "ranking" : 5
  }, {
    "nome" : "SEVERINA",
    "frequencia" : 122,
    "ranking" : 6
  }, {
    "nome" : "ANA",
    "frequencia" : 104,
    "ranking" : 7
  }, {
    "nome" : "JOSEFA",
    "frequencia" : 90,
    "ranking" : 8
  }, {
    "nome" : "MANOEL",
    "frequencia" : 79,
    "ranking" : 9
  }, {
    "nome" : "FRANCISCO",
    "frequencia" : 77,
    "ranking" : 10
  }, {
    "nome" : "LUIZ",
    "frequencia" : 58,
    "ranking" : 11
  }, {
    "nome" : "PEDRO",
    "frequencia" : 54,
    "ranking" : 12
  }, {
    "nome" : "CARLOS",
    "frequencia" : 43,
    "ranking" : 13
  }, {
    "nome" : "PAULO",
    "frequencia" : 35,
    "ranking" : 14
  }, {
    "nome" : "SEBASTIAO",
    "frequencia" : 32,
    "ranking" : 15
  }, {
    "nome" : "TEREZINHA",
    "frequencia" : 27,
    "ranking" : 16
  }, {
    "nome" : "LUIS",
    "frequencia" : 27,
    "ranking" : 17
  }, {
    "nome" : "GERALDO",
    "frequencia" : 25,
    "ranking" : 18
  }, {
    "nome" : "DANIEL",
    "frequencia" : 24,
    "ranking" : 19
  }, {
    "nome" : "FRANCISCA",
    "frequencia" : 23,
    "ranking" : 22
  } ]
} ]