[ {
  "localidade" : "3547007",
  "sexo" : null,
  "res" : [ {
    "nome" : "MARIA",
    "frequencia" : 341,
    "ranking" : 1
  }, {
    "nome" : "JOSE",
    "frequencia" : 202,
    "ranking" : 2
  }, {
    "nome" : "JOAO",
    "frequencia" : 121,
    "ranking" : 3
  }, {
    "nome" : "ANA",
    "frequencia" : 107,
    "ranking" : 4
  }, {
    "nome" : "ANTONIO",
    "frequencia" : 105,
    "ranking" : 5
  }, {
    "nome" : "LUIS",
    "frequencia" : 77,
    "ranking" : 6
  }, {
    "nome" : "BENEDITO",
    "frequencia" : 52,
    "ranking" : 7
  }, {
    "nome" : "CARLOS",
    "frequencia" : 48,
    "ranking" : 8
  }, {
    "nome" : "PAULO",
    "frequencia" : 41,
    "ranking" : 10
  }, {
    "nome" : "PEDRO",
    "frequencia" : 41,
    "ranking" : 9
  }, {
    "nome" : "LUCAS",
    "frequencia" : 36,
    "ranking" : 11
  }, {
    "nome" : "GABRIEL",
    "frequencia" : 31,
    "ranking" : 12
  }, {
    "nome" : "MARCOS",
    "frequencia" : 28,
    "ranking" : 13
  }, {
    "nome" : "FRANCISCO",
    "frequencia" : 27,
    "ranking" : 14
  }, {
    "nome" : "LUIZ",
    "frequencia" : 26,
    "ranking" : 15
  }, {
    "nome" : "APARECIDA",
    "frequencia" : 23,
    "ranking" : 16
  }, {
    "nome" : "JULIANA",
    "frequencia" : 22,
    "ranking" : 18
  }, {
    "nome" : "MATEUS",
    "frequencia" : 22,
    "ranking" : 17
  }, {
    "nome" : "LEANDRO",
    "frequencia" : 21,
    "ranking" : 19
  }, {
    "nome" : "RAFAEL",
    "frequencia" : 20,
    "ranking" : 20
  } ]
} ]