[ {
  "localidade" : "2917607",
  "sexo" : null,
  "res" : [ {
    "nome" : "MARIA",
    "frequencia" : 2578,
    "ranking" : 1
  }, {
    "nome" : "JOSE",
    "frequencia" : 997,
    "ranking" : 2
  }, {
    "nome" : "ANTONIO",
    "frequencia" : 868,
    "ranking" : 3
  }, {
    "nome" : "JOAO",
    "frequencia" : 611,
    "ranking" : 4
  }, {
    "nome" : "ANA",
    "frequencia" : 587,
    "ranking" : 5
  }, {
    "nome" : "CARLOS",
    "frequencia" : 335,
    "ranking" : 6
  }, {
    "nome" : "MARCOS",
    "frequencia" : 301,
    "ranking" : 7
  }, {
    "nome" : "MANOEL",
    "frequencia" : 288,
    "ranking" : 8
  }, {
    "nome" : "LUCAS",
    "frequencia" : 269,
    "ranking" : 9
  }, {
    "nome" : "PAULO",
    "frequencia" : 241,
    "ranking" : 10
  }, {
    "nome" : "PEDRO",
    "frequencia" : 210,
    "ranking" : 11
  }, {
    "nome" : "DANIEL",
    "frequencia" : 207,
    "ranking" : 12
  }, {
    "nome" : "MATEUS",
    "frequencia" : 188,
    "ranking" : 13
  }, {
    "nome" : "GABRIEL",
    "frequencia" : 186,
    "ranking" : 14
  }, {
    "nome" : "MANUEL",
    "frequencia" : 173,
    "ranking" : 15
  }, {
    "nome" : "LUIZ",
    "frequencia" : 163,
    "ranking" : 16
  }, {
    "nome" : "RAFAEL",
    "frequencia" : 151,
    "ranking" : 17
  }, {
    "nome" : "TIAGO",
    "frequencia" : 150,
    "ranking" : 18
  }, {
    "nome" : "ANTONIA",
    "frequencia" : 149,
    "ranking" : 19
  }, {
    "nome" : "FABIO",
    "frequencia" : 141,
    "ranking" : 20
  } ]
} ]