[ {
  "localidade" : "5106232",
  "sexo" : null,
  "res" : [ {
    "nome" : "MARIA",
    "frequencia" : 1099,
    "ranking" : 1
  }, {
    "nome" : "JOSE",
    "frequencia" : 855,
    "ranking" : 2
  }, {
    "nome" : "JOAO",
    "frequencia" : 285,
    "ranking" : 3
  }, {
    "nome" : "ANA",
    "frequencia" : 239,
    "ranking" : 4
  }, {
    "nome" : "ANTONIO",
    "frequencia" : 222,
    "ranking" : 5
  }, {
    "nome" : "CARLOS",
    "frequencia" : 122,
    "ranking" : 6
  }, {
    "nome" : "LUCAS",
    "frequencia" : 119,
    "ranking" : 7
  }, {
    "nome" : "LUIZ",
    "frequencia" : 113,
    "ranking" : 8
  }, {
    "nome" : "FRANCISCO",
    "frequencia" : 107,
    "ranking" : 9
  }, {
    "nome" : "PAULO",
    "frequencia" : 104,
    "ranking" : 10
  }, {
    "nome" : "PEDRO",
    "frequencia" : 96,
    "ranking" : 11
  }, {
    "nome" : "MANOEL",
    "frequencia" : 94,
    "ranking" : 12
  }, {
    "nome" : "CICERO",
    "frequencia" : 94,
    "ranking" : 13
  }, {
    "nome" : "MARCOS",
    "frequencia" : 86,
    "ranking" : 14
  }, {
    "nome" : "GABRIEL",
    "frequencia" : 71,
    "ranking" : 15
  }, {
    "nome" : "DANIEL",
    "frequencia" : 65,
    "ranking" : 16
  }, {
    "nome" : "RAFAEL",
    "frequencia" : 58,
    "ranking" : 17
  }, {
    "nome" : "EDUARDO",
    "frequencia" : 55,
    "ranking" : 18
  }, {
    "nome" : "FABIO",
    "frequencia" : 53,
    "ranking" : 21
  }, {
    "nome" : "ADRIANA",
    "frequencia" : 53,
    "ranking" : 20
  } ]
} ]