[ {
  "localidade" : "2509800",
  "sexo" : null,
  "res" : [ {
    "nome" : "MARIA",
    "frequencia" : 1251,
    "ranking" : 1
  }, {
    "nome" : "JOSE",
    "frequencia" : 658,
    "ranking" : 2
  }, {
    "nome" : "ANTONIO",
    "frequencia" : 262,
    "ranking" : 3
  }, {
    "nome" : "JOAO",
    "frequencia" : 244,
    "ranking" : 4
  }, {
    "nome" : "SEVERINO",
    "frequencia" : 203,
    "ranking" : 5
  }, {
    "nome" : "JOSEFA",
    "frequencia" : 147,
    "ranking" : 6
  }, {
    "nome" : "SEVERINA",
    "frequencia" : 137,
    "ranking" : 7
  }, {
    "nome" : "ANA",
    "frequencia" : 122,
    "ranking" : 8
  }, {
    "nome" : "MANOEL",
    "frequencia" : 81,
    "ranking" : 9
  }, {
    "nome" : "LUIS",
    "frequencia" : 72,
    "ranking" : 10
  }, {
    "nome" : "FRANCISCO",
    "frequencia" : 71,
    "ranking" : 11
  }, {
    "nome" : "ANTONIA",
    "frequencia" : 48,
    "ranking" : 12
  }, {
    "nome" : "PEDRO",
    "frequencia" : 46,
    "ranking" : 13
  }, {
    "nome" : "MARCOS",
    "frequencia" : 45,
    "ranking" : 14
  }, {
    "nome" : "CARLOS",
    "frequencia" : 44,
    "ranking" : 15
  }, {
    "nome" : "LUIZ",
    "frequencia" : 37,
    "ranking" : 16
  }, {
    "nome" : "RITA",
    "frequencia" : 36,
    "ranking" : 17
  }, {
    "nome" : "LUCIANO",
    "frequencia" : 35,
    "ranking" : 18
  }, {
    "nome" : "PAULO",
    "frequencia" : 33,
    "ranking" : 19
  }, {
    "nome" : "LUCAS",
    "frequencia" : 32,
    "ranking" : 20
  } ]
} ]