[ {
  "localidade" : "4103503",
  "sexo" : null,
  "res" : [ {
    "nome" : "MARIA",
    "frequencia" : 498,
    "ranking" : 1
  }, {
    "nome" : "JOSE",
    "frequencia" : 285,
    "ranking" : 2
  }, {
    "nome" : "JOAO",
    "frequencia" : 186,
    "ranking" : 3
  }, {
    "nome" : "ANTONIO",
    "frequencia" : 113,
    "ranking" : 4
  }, {
    "nome" : "ANA",
    "frequencia" : 96,
    "ranking" : 5
  }, {
    "nome" : "PAULO",
    "frequencia" : 83,
    "ranking" : 6
  }, {
    "nome" : "LUIZ",
    "frequencia" : 79,
    "ranking" : 7
  }, {
    "nome" : "PEDRO",
    "frequencia" : 68,
    "ranking" : 8
  }, {
    "nome" : "CARLOS",
    "frequencia" : 66,
    "ranking" : 9
  }, {
    "nome" : "LUCAS",
    "frequencia" : 58,
    "ranking" : 10
  }, {
    "nome" : "MARCOS",
    "frequencia" : 53,
    "ranking" : 11
  }, {
    "nome" : "LUIS",
    "frequencia" : 45,
    "ranking" : 12
  }, {
    "nome" : "SEBASTIAO",
    "frequencia" : 42,
    "ranking" : 13
  }, {
    "nome" : "APARECIDA",
    "frequencia" : 39,
    "ranking" : 14
  }, {
    "nome" : "MARCELO",
    "frequencia" : 38,
    "ranking" : 15
  }, {
    "nome" : "GABRIEL",
    "frequencia" : 36,
    "ranking" : 16
  }, {
    "nome" : "LEANDRO",
    "frequencia" : 33,
    "ranking" : 17
  }, {
    "nome" : "GUSTAVO",
    "frequencia" : 32,
    "ranking" : 19
  }, {
    "nome" : "MARCIA",
    "frequencia" : 32,
    "ranking" : 18
  }, {
    "nome" : "LEONARDO",
    "frequencia" : 31,
    "ranking" : 20
  } ]
} ]