[ {
  "localidade" : "3127701",
  "sexo" : null,
  "res" : [ {
    "nome" : "MARIA",
    "frequencia" : 16310,
    "ranking" : 1
  }, {
    "nome" : "JOSE",
    "frequencia" : 6748,
    "ranking" : 2
  }, {
    "nome" : "ANA",
    "frequencia" : 4401,
    "ranking" : 3
  }, {
    "nome" : "JOAO",
    "frequencia" : 3433,
    "ranking" : 4
  }, {
    "nome" : "ANTONIO",
    "frequencia" : 2124,
    "ranking" : 5
  }, {
    "nome" : "CARLOS",
    "frequencia" : 1882,
    "ranking" : 6
  }, {
    "nome" : "LUCAS",
    "frequencia" : 1879,
    "ranking" : 7
  }, {
    "nome" : "PAULO",
    "frequencia" : 1800,
    "ranking" : 8
  }, {
    "nome" : "MARCOS",
    "frequencia" : 1759,
    "ranking" : 9
  }, {
    "nome" : "PEDRO",
    "frequencia" : 1669,
    "ranking" : 10
  }, {
    "nome" : "GERALDO",
    "frequencia" : 1604,
    "ranking" : 11
  }, {
    "nome" : "GABRIEL",
    "frequencia" : 1521,
    "ranking" : 12
  }, {
    "nome" : "DANIEL",
    "frequencia" : 1273,
    "ranking" : 13
  }, {
    "nome" : "LUIZ",
    "frequencia" : 1222,
    "ranking" : 14
  }, {
    "nome" : "MATEUS",
    "frequencia" : 1154,
    "ranking" : 15
  }, {
    "nome" : "RAFAEL",
    "frequencia" : 1152,
    "ranking" : 16
  }, {
    "nome" : "SEBASTIAO",
    "frequencia" : 1020,
    "ranking" : 17
  }, {
    "nome" : "MARCELO",
    "frequencia" : 928,
    "ranking" : 18
  }, {
    "nome" : "BRUNO",
    "frequencia" : 909,
    "ranking" : 19
  }, {
    "nome" : "LETICIA",
    "frequencia" : 848,
    "ranking" : 20
  } ]
} ]