[ {
  "localidade" : "3519303",
  "sexo" : null,
  "res" : [ {
    "nome" : "MARIA",
    "frequencia" : 1504,
    "ranking" : 1
  }, {
    "nome" : "JOSE",
    "frequencia" : 981,
    "ranking" : 2
  }, {
    "nome" : "ANA",
    "frequencia" : 493,
    "ranking" : 3
  }, {
    "nome" : "JOAO",
    "frequencia" : 464,
    "ranking" : 4
  }, {
    "nome" : "ANTONIO",
    "frequencia" : 430,
    "ranking" : 5
  }, {
    "nome" : "CARLOS",
    "frequencia" : 278,
    "ranking" : 6
  }, {
    "nome" : "PAULO",
    "frequencia" : 267,
    "ranking" : 7
  }, {
    "nome" : "LUIS",
    "frequencia" : 224,
    "ranking" : 8
  }, {
    "nome" : "MARCOS",
    "frequencia" : 212,
    "ranking" : 9
  }, {
    "nome" : "LUCAS",
    "frequencia" : 211,
    "ranking" : 10
  }, {
    "nome" : "LUIZ",
    "frequencia" : 176,
    "ranking" : 11
  }, {
    "nome" : "APARECIDA",
    "frequencia" : 176,
    "ranking" : 12
  }, {
    "nome" : "PEDRO",
    "frequencia" : 174,
    "ranking" : 13
  }, {
    "nome" : "GABRIEL",
    "frequencia" : 166,
    "ranking" : 14
  }, {
    "nome" : "MARCELO",
    "frequencia" : 156,
    "ranking" : 15
  }, {
    "nome" : "LEANDRO",
    "frequencia" : 138,
    "ranking" : 16
  }, {
    "nome" : "DANIEL",
    "frequencia" : 132,
    "ranking" : 17
  }, {
    "nome" : "BRUNO",
    "frequencia" : 127,
    "ranking" : 18
  }, {
    "nome" : "FRANCISCO",
    "frequencia" : 127,
    "ranking" : 19
  }, {
    "nome" : "RAFAEL",
    "frequencia" : 122,
    "ranking" : 20
  } ]
} ]