[ {
  "localidade" : "3515103",
  "sexo" : null,
  "res" : [ {
    "nome" : "MARIA",
    "frequencia" : 2921,
    "ranking" : 1
  }, {
    "nome" : "JOSE",
    "frequencia" : 1655,
    "ranking" : 2
  }, {
    "nome" : "JOAO",
    "frequencia" : 873,
    "ranking" : 3
  }, {
    "nome" : "ANA",
    "frequencia" : 826,
    "ranking" : 4
  }, {
    "nome" : "ANTONIO",
    "frequencia" : 729,
    "ranking" : 5
  }, {
    "nome" : "PAULO",
    "frequencia" : 496,
    "ranking" : 6
  }, {
    "nome" : "CARLOS",
    "frequencia" : 476,
    "ranking" : 7
  }, {
    "nome" : "LUCAS",
    "frequencia" : 430,
    "ranking" : 8
  }, {
    "nome" : "PEDRO",
    "frequencia" : 375,
    "ranking" : 9
  }, {
    "nome" : "GABRIEL",
    "frequencia" : 369,
    "ranking" : 10
  }, {
    "nome" : "MARCOS",
    "frequencia" : 362,
    "ranking" : 11
  }, {
    "nome" : "LUIS",
    "frequencia" : 337,
    "ranking" : 12
  }, {
    "nome" : "RAFAEL",
    "frequencia" : 331,
    "ranking" : 13
  }, {
    "nome" : "BRUNO",
    "frequencia" : 308,
    "ranking" : 14
  }, {
    "nome" : "FELIPE",
    "frequencia" : 306,
    "ranking" : 15
  }, {
    "nome" : "LUIZ",
    "frequencia" : 296,
    "ranking" : 16
  }, {
    "nome" : "MARCELO",
    "frequencia" : 286,
    "ranking" : 17
  }, {
    "nome" : "FRANCISCO",
    "frequencia" : 267,
    "ranking" : 18
  }, {
    "nome" : "DANIEL",
    "frequencia" : 258,
    "ranking" : 19
  }, {
    "nome" : "GUSTAVO",
    "frequencia" : 257,
    "ranking" : 21
  } ]
} ]