[ {
  "localidade" : "3155405",
  "sexo" : null,
  "res" : [ {
    "nome" : "MARIA",
    "frequencia" : 596,
    "ranking" : 1
  }, {
    "nome" : "JOSE",
    "frequencia" : 352,
    "ranking" : 2
  }, {
    "nome" : "ANA",
    "frequencia" : 221,
    "ranking" : 3
  }, {
    "nome" : "JOAO",
    "frequencia" : 144,
    "ranking" : 4
  }, {
    "nome" : "CARLOS",
    "frequencia" : 117,
    "ranking" : 5
  }, {
    "nome" : "LUIZ",
    "frequencia" : 110,
    "ranking" : 6
  }, {
    "nome" : "ANTONIO",
    "frequencia" : 105,
    "ranking" : 7
  }, {
    "nome" : "PAULO",
    "frequencia" : 95,
    "ranking" : 8
  }, {
    "nome" : "GERALDO",
    "frequencia" : 89,
    "ranking" : 9
  }, {
    "nome" : "SEBASTIAO",
    "frequencia" : 85,
    "ranking" : 10
  }, {
    "nome" : "LUIS",
    "frequencia" : 57,
    "ranking" : 11
  }, {
    "nome" : "LUCAS",
    "frequencia" : 50,
    "ranking" : 12
  }, {
    "nome" : "PEDRO",
    "frequencia" : 49,
    "ranking" : 13
  }, {
    "nome" : "GABRIEL",
    "frequencia" : 40,
    "ranking" : 14
  }, {
    "nome" : "FRANCISCO",
    "frequencia" : 40,
    "ranking" : 15
  }, {
    "nome" : "JORGE",
    "frequencia" : 39,
    "ranking" : 16
  }, {
    "nome" : "JULIANA",
    "frequencia" : 38,
    "ranking" : 17
  }, {
    "nome" : "MARCELO",
    "frequencia" : 38,
    "ranking" : 20
  }, {
    "nome" : "RAFAEL",
    "frequencia" : 38,
    "ranking" : 19
  }, {
    "nome" : "MARCOS",
    "frequencia" : 38,
    "ranking" : 18
  } ]
} ]