[ {
  "localidade" : "1301902",
  "sexo" : null,
  "res" : [ {
    "nome" : "MARIA",
    "frequencia" : 4001,
    "ranking" : 1
  }, {
    "nome" : "JOSE",
    "frequencia" : 1720,
    "ranking" : 2
  }, {
    "nome" : "RAIMUNDO",
    "frequencia" : 1163,
    "ranking" : 3
  }, {
    "nome" : "ANA",
    "frequencia" : 1065,
    "ranking" : 4
  }, {
    "nome" : "JOAO",
    "frequencia" : 1032,
    "ranking" : 5
  }, {
    "nome" : "ANTONIO",
    "frequencia" : 950,
    "ranking" : 6
  }, {
    "nome" : "FRANCISCO",
    "frequencia" : 788,
    "ranking" : 7
  }, {
    "nome" : "CARLOS",
    "frequencia" : 547,
    "ranking" : 8
  }, {
    "nome" : "RAIMUNDA",
    "frequencia" : 538,
    "ranking" : 9
  }, {
    "nome" : "PAULO",
    "frequencia" : 508,
    "ranking" : 10
  }, {
    "nome" : "PEDRO",
    "frequencia" : 468,
    "ranking" : 11
  }, {
    "nome" : "MANOEL",
    "frequencia" : 444,
    "ranking" : 12
  }, {
    "nome" : "LUCAS",
    "frequencia" : 411,
    "ranking" : 13
  }, {
    "nome" : "LUIZ",
    "frequencia" : 375,
    "ranking" : 14
  }, {
    "nome" : "MARCOS",
    "frequencia" : 372,
    "ranking" : 15
  }, {
    "nome" : "GABRIEL",
    "frequencia" : 352,
    "ranking" : 16
  }, {
    "nome" : "DANIEL",
    "frequencia" : 332,
    "ranking" : 17
  }, {
    "nome" : "FELIPE",
    "frequencia" : 302,
    "ranking" : 18
  }, {
    "nome" : "MATEUS",
    "frequencia" : 264,
    "ranking" : 19
  }, {
    "nome" : "FRANCISCA",
    "frequencia" : 249,
    "ranking" : 20
  } ]
} ]