[ {
  "localidade" : "3509700",
  "sexo" : null,
  "res" : [ {
    "nome" : "MARIA",
    "frequencia" : 2864,
    "ranking" : 1
  }, {
    "nome" : "JOSE",
    "frequencia" : 1649,
    "ranking" : 2
  }, {
    "nome" : "ANA",
    "frequencia" : 991,
    "ranking" : 3
  }, {
    "nome" : "JOAO",
    "frequencia" : 843,
    "ranking" : 4
  }, {
    "nome" : "LUIZ",
    "frequencia" : 685,
    "ranking" : 5
  }, {
    "nome" : "ANTONIO",
    "frequencia" : 511,
    "ranking" : 6
  }, {
    "nome" : "CARLOS",
    "frequencia" : 444,
    "ranking" : 7
  }, {
    "nome" : "PAULO",
    "frequencia" : 416,
    "ranking" : 8
  }, {
    "nome" : "PEDRO",
    "frequencia" : 383,
    "ranking" : 9
  }, {
    "nome" : "LUCAS",
    "frequencia" : 359,
    "ranking" : 10
  }, {
    "nome" : "BENEDITO",
    "frequencia" : 352,
    "ranking" : 11
  }, {
    "nome" : "MARCOS",
    "frequencia" : 320,
    "ranking" : 12
  }, {
    "nome" : "LUIS",
    "frequencia" : 314,
    "ranking" : 13
  }, {
    "nome" : "GABRIEL",
    "frequencia" : 273,
    "ranking" : 14
  }, {
    "nome" : "RAFAEL",
    "frequencia" : 258,
    "ranking" : 16
  }, {
    "nome" : "SEBASTIAO",
    "frequencia" : 258,
    "ranking" : 15
  }, {
    "nome" : "BENEDITA",
    "frequencia" : 236,
    "ranking" : 17
  }, {
    "nome" : "FELIPE",
    "frequencia" : 234,
    "ranking" : 18
  }, {
    "nome" : "DANIEL",
    "frequencia" : 233,
    "ranking" : 19
  }, {
    "nome" : "MARCELO",
    "frequencia" : 229,
    "ranking" : 20
  } ]
} ]