[ {
  "localidade" : "2700409",
  "sexo" : null,
  "res" : [ {
    "nome" : "MARIA",
    "frequencia" : 5423,
    "ranking" : 1
  }, {
    "nome" : "JOSE",
    "frequencia" : 4886,
    "ranking" : 2
  }, {
    "nome" : "CICERO",
    "frequencia" : 634,
    "ranking" : 4
  }, {
    "nome" : "ANA",
    "frequencia" : 634,
    "ranking" : 3
  }, {
    "nome" : "JOAO",
    "frequencia" : 625,
    "ranking" : 5
  }, {
    "nome" : "ANTONIO",
    "frequencia" : 505,
    "ranking" : 6
  }, {
    "nome" : "JOSEFA",
    "frequencia" : 430,
    "ranking" : 7
  }, {
    "nome" : "CARLOS",
    "frequencia" : 342,
    "ranking" : 8
  }, {
    "nome" : "LUIZ",
    "frequencia" : 317,
    "ranking" : 9
  }, {
    "nome" : "PAULO",
    "frequencia" : 282,
    "ranking" : 10
  }, {
    "nome" : "PEDRO",
    "frequencia" : 252,
    "ranking" : 11
  }, {
    "nome" : "CICERA",
    "frequencia" : 224,
    "ranking" : 12
  }, {
    "nome" : "MANOEL",
    "frequencia" : 215,
    "ranking" : 13
  }, {
    "nome" : "LUIS",
    "frequencia" : 191,
    "ranking" : 14
  }, {
    "nome" : "LUCAS",
    "frequencia" : 189,
    "ranking" : 15
  }, {
    "nome" : "BENEDITO",
    "frequencia" : 188,
    "ranking" : 16
  }, {
    "nome" : "MARCOS",
    "frequencia" : 162,
    "ranking" : 17
  }, {
    "nome" : "FRANCISCO",
    "frequencia" : 160,
    "ranking" : 18
  }, {
    "nome" : "EDUARDO",
    "frequencia" : 147,
    "ranking" : 19
  }, {
    "nome" : "SEBASTIAO",
    "frequencia" : 138,
    "ranking" : 20
  } ]
} ]